{
	"configurations" : 
	[
		{
			"directories" : 
			[
				{
					"build" : ".",
					"hasInstallRule" : true,
					"jsonFile" : "directory-.-Debug-0d65f6c4000d4c0ca67d.json",
					"minimumCMakeVersion" : 
					{
						"string" : "3.8"
					},
					"projectIndex" : 0,
					"source" : ".",
					"targetIndexes" : 
					[
						0,
						1,
						2
					]
				}
			],
			"name" : "Debug",
			"projects" : 
			[
				{
					"directoryIndexes" : 
					[
						0
					],
					"name" : "my_robot_motion_planning",
					"targetIndexes" : 
					[
						0,
						1,
						2
					]
				}
			],
			"targets" : 
			[
				{
					"directoryIndex" : 0,
					"id" : "my_motion_planner::@6890427a1f51a3e7e1df",
					"jsonFile" : "target-my_motion_planner-Debug-416b03f01bd3c2ee2090.json",
					"name" : "my_motion_planner",
					"projectIndex" : 0
				},
				{
					"directoryIndex" : 0,
					"id" : "my_robot_motion_planning_uninstall::@6890427a1f51a3e7e1df",
					"jsonFile" : "target-my_robot_motion_planning_uninstall-Debug-d73e29137613215af020.json",
					"name" : "my_robot_motion_planning_uninstall",
					"projectIndex" : 0
				},
				{
					"directoryIndex" : 0,
					"id" : "uninstall::@6890427a1f51a3e7e1df",
					"jsonFile" : "target-uninstall-Debug-fef18350f04e127ac3ef.json",
					"name" : "uninstall",
					"projectIndex" : 0
				}
			]
		}
	],
	"kind" : "codemodel",
	"paths" : 
	{
		"build" : "/root/ros2_ws/build",
		"source" : "/root/ros2_ws"
	},
	"version" : 
	{
		"major" : 2,
		"minor" : 3
	}
}
